[
    {
        "name": "Новые Альбомы",
        "gid": 4100014,
        "members_count": 541924
    },
    {
        "name": "Synthpop [Futurepop, Retrowave, Electropop]",
        "gid": 8564,
        "members_count": 25494
    },
    {
        "name": "СИЛА",
        "gid": 151498735,
        "members_count": 544080
    },
    {
        "name": "E:\\music\\leftfield",
        "gid": 101522128,
        "members_count": 12457
    },
    {
        "name": "Depeche Mode",
        "gid": 125927592,
        "members_count": 152811
    },
    {
        "name": "Другая Музыка",
        "gid": 35486626,
        "members_count": 864747
    },
    {
        "name": "E:\\music\\trip-hop",
        "gid": 27683540,
        "members_count": 87350
    }
]